README.rst
setup.cfg
setup.py
django_postalcodes_light.egg-info/PKG-INFO
django_postalcodes_light.egg-info/SOURCES.txt
django_postalcodes_light.egg-info/dependency_links.txt
django_postalcodes_light.egg-info/not-zip-safe
django_postalcodes_light.egg-info/requires.txt
django_postalcodes_light.egg-info/top_level.txt
postalcodes_light/__init__.py
postalcodes_light/admin.py
postalcodes_light/models.py
postalcodes_light/management/__init__.py
postalcodes_light/management/commands/__init__.py
postalcodes_light/management/commands/import_postalcodes.py
postalcodes_light/migrations/0001_initial.py
postalcodes_light/migrations/0002_unique_together.py
postalcodes_light/migrations/__init__.py