Metadata-Version: 1.1
Name: django-postalcodes-light
Version: 0.2.0
Summary: Postal code management (without the PostGIS requirement).
Home-page: https://github.com/tobiasmcnulty/django-postalcodes-light/
Author: Tobias McNulty
Author-email: tobias.mcnulty@gmail.com
License: BSD License
Platform: OS Independent
Classifier: Development Status :: 3 - Alpha
Classifier: Environment :: Web Environment
Classifier: Intended Audience :: Developers
Classifier: License :: OSI Approved :: BSD License
Classifier: Operating System :: OS Independent
Classifier: Programming Language :: Python
Classifier: Framework :: Django
